ng2nlm/__init__.py
ng2nlm/__main__.py
ng2nlm/ng2nlm.py
ng2nlm/py.typed
ng2nlm-1.1.0.dist-info/WHEEL
ng2nlm-1.1.0.dist-info/entry_points.txt
ng2nlm-1.1.0.dist-info/METADATA
ng2nlm-1.1.0.dist-info/RECORD
