Metadata-Version: 2.4
Name: ng2nlm
Version: 1.1.0
Summary: Convert a Norton Guide database into a source for NotebookLM
Keywords: obsidian,notebooklm,ai,llm,machine-learning,norton-guide,help,ms-dos,clipper,xbase,dbase
Author: Dave Pearson
Author-email: Dave Pearson <davep@davep.org>
License-Expression: GPL-3.0-or-later
Classifier: Development Status :: 5 - Production/Stable
Classifier: Environment :: Console
Classifier: Intended Audience :: Developers
Classifier: Intended Audience :: End Users/Desktop
Classifier: Intended Audience :: Information Technology
Classifier: Intended Audience :: Other Audience
Classifier: Operating System :: OS Independent
Classifier: Programming Language :: Python :: 3 :: Only
Classifier: Programming Language :: Python :: 3
Classifier: Programming Language :: Python :: 3.13
Classifier: Programming Language :: Python :: 3.14
Classifier: Topic :: Documentation
Classifier: Topic :: Software Development :: Documentation
Classifier: Topic :: Text Processing :: Markup :: Markdown
Classifier: Topic :: Utilities
Classifier: Typing :: Typed
Requires-Dist: ngdb>=1.2.0
Requires-Python: >=3.13
Project-URL: Discussions, https://github.com/davep/ng2nlm/discussions
Project-URL: Documentation, https://ng2nlm.davep.dev/
Project-URL: Homepage, https://ng2nlm.davep.dev/
Project-URL: Issues, https://github.com/davep/ng2nlm/issues
Project-URL: Repository, https://github.com/davep/ng2nlm
Project-URL: Source, https://github.com/davep/ng2nlm
